{"fecha": "19-03-2026", "evangelio": "san Mateo 1, 16. 18-21. 24a", "texto_evangelio": "Nacimiento de Jesucristo\n16 y Jacob, padre de José, que fue el esposo de María, de la cual nació Jesús llamado el Cristo.\n18 El nacimiento de Jesucristo fue así: Su madre, María, estaba comprometida para casarse con José; pero, antes de unirse a él, resultó que estaba embarazada por el poder del Espíritu Santo.  19 Como José, su esposo, era un hombre justo y no quería exponerla a vergüenza pública, decidió romper en secreto el compromiso.\n20 Pero cuando él estaba considerando hacerlo, se le apareció en sueños un ángel del Señor y le dijo: «José, hijo de David, no temas recibir a María por esposa, porque ella ha concebido por el poder del Espíritu Santo.  21 Dará a luz un hijo y le pondrás por nombre Jesús, porque él salvará a su pueblo de sus pecados».\n24 Cuando José se despertó, hizo lo que el ángel del Señor le había mandado y recibió a María por esposa.  ", "oracion": "**Título:**  \nLa llamada de José: confianza y obediencia en el misterio de Dios\n\n---\n\n**Relajación:**  \nEncuentra un lugar cómodo y tranquilo donde puedas sentarte sin interrupciones durante unos minutos. Cierra suavemente los ojos, respira profundo un par de veces, dejando que la tensión se disuelva. Siente cómo tu cuerpo se asienta en el espacio, dispuesto para encontrarte con Dios y su palabra.\n\n---\n\n**Petición:**  \nSeñor, ayúdame a confiar como José en tu plan de amor.\n\n---\n\n**Método de oración Ignaciana:** Meditación\n\nLa meditación en el método ignaciano consiste en reflexionar activamente el texto bíblico, buscando captar el mensaje y aplicarlo al corazón y vida. Es un diálogo interior que invita a preguntarse y responder, escuchando lo que el Señor quiere decirnos hoy.\n\n---\n\n**Guía para la Meditación (Mateo 1,16.18-21.24a):**\n\n1. **¿Qué significa para mí la experiencia de José al recibir con humildad y obediencia el anuncio del ángel?**  \n   Reflexiona sobre la sorpresa, dudas o temores que pudo tener, y cómo él decide fiarse de Dios a pesar de las circunstancias inesperadas.\n\n2. **¿Cómo reconozco en mi vida los momentos en que Dios me llama a aceptar un misterio o responsabilidad difícil?**  \n   Piensa en tu propia respuesta: ¿pongo obstáculos o doy pasos de fe como José?\n\n3. **¿De qué manera puedo ser instrumento de la voluntad de Dios hoy, cuidando las personas y situaciones que me ha confiado?**  \n   Invita al Señor a enseñarte a vivir tu misión con generosidad y confianza.\n\n---\n\n**Coloquio (Diálogo con Dios):**\n\nSeñor Jesús, como José, me encuentro a veces confundido y temeroso ante tus planes que no comprendo del todo. Te pido la gracia de abrir mi corazón y escuchar sin resistencia. Dame fuerza para obedecer como él, poniéndote al centro de mi vida. Ayúdame a ser un guardián fiel, que protege no sólo con hechos, sino con amor profundo y presencia constante. Quiero aprender a decir sí contigo y a fiarme aunque el camino sea incierto. Quédate conmigo y camina a mi lado. Gracias por tu amor que siempre me sostiene.\n\n---\n\n**Breve explicación del Examen Ignaciano:**  \nEl examen es un momento diario para revisar el día en presencia de Dios, buscando reconocer dónde he estado más abierto a su amor y dónde me he alejado. Me ayuda a crecer en conciencia espiritual, agradecer los dones recibidos y pedir perdón y ayuda para mejorar. Es una invitación a dejar que el Señor ilumine mi vida y camine conmigo siempre.\n\n---\n\nQue esta oración te acompañe en tu caminar, iluminando con la luz de la fe el misterio de amor que Dios realiza en cada uno de nosotros. Amén.", "reflexion": "Te invito primero a que encuentres un lugar tranquilo, donde puedas sentarte o recostarte cómodamente. Cierra los ojos suavemente, respira profundamente varias veces, inhalando paz y exhalando cualquier tensión o preocupación. Permite que tu cuerpo se relaje y tu mente se abra, soltando el ritmo acelerado del día para estar presente en este momento de reflexión.\n\nEn ocasiones, la vida nos presenta situaciones inesperadas que pueden parecer confusas o difíciles de comprender al principio. Puede ser un camino lleno de incertidumbres, dudas y decisiones que desafían lo que creíamos seguro o real. Sin embargo, en medio de estas circunstancias, existe una fuerza interior para mirar más allá del miedo y la inquietud, y encontrar un propósito que ilumine nuestro paso.\n\nCuando algo nuevo está por manifestarse en nuestra existencia, es natural que surjan dudas o temores sobre cómo responderemos a ese cambio. Pero es justamente ahí donde podemos descubrir una invitación profunda: la de aceptar la responsabilidad de nuestras propias transformaciones. No siempre podemos controlar las circunstancias externas, pero sí podemos elegir nuestra forma de actuar frente a ellas.\n\nEn ese proceso, a veces se presenta una llamada a confiar en la voz de la intuición o en esa sensación interna que apunta hacia un camino más auténtico, un camino alineado con lo que realmente queremos ser y aportar al mundo. No es un camino sin desafíos, pero sí es un camino lleno de significado, uno que nos lleva a hacer aquello que puede traer un impacto positivo, no solo para nosotros, sino también para quienes nos rodean.\n\nTambién es importante reconocer que actuar con integridad y compromiso no significa hacerlo solos; muchas veces, viene acompañado del apoyo silencioso o visible de quienes confían en nosotros, de nuestra capacidad para escuchar y dejarnos guiar por esa fuerza que impulsa a hacer lo correcto más allá de los miedos. Al aceptar esa tarea, descubrimos que dentro de cada responsabilidad hay una semilla de esperanza y renovación.\n\nTe invito a que al reflexionar sobre esos momentos en tu vida en que tuviste que tomar una decisión difícil o aceptar un rol que parecía más grande que tú, recuerdes cómo encontraste fuerza en tu interior para seguir adelante. Pregúntate ahora: ¿qué situación actual me pide esa misma valentía? ¿Qué mensaje tengo que descubrir más allá del miedo o la duda?\n\nQuizás este sea el momento para abrirte a nuevas posibilidades, para permitir que algo inesperado crezca y transforme tu presente y tu futuro. Recuerda que cada paso hacia adelante puede estar guiado por un propósito más profundo, una razón que conecta con tu deseo de aportar, de construir o simplemente de vivir con más autenticidad y sentido.\n\nTermina esta reflexión regresando suavemente a tu respiración, agradeciendo la oportunidad de conectarte con estas preguntas internas. Cuando estés listo, abre tus ojos lentamente, llevando contigo la calma y el compromiso de escuchar y acompañar tu camino con valor y esperanza.", "mision": "Que en el silencio del corazón encontremos valor para aceptar el amor que transforma nuestra vida."}